simple_mysql.py
simple_mysql-1.0.4.dist-info/LICENSE
simple_mysql-1.0.4.dist-info/METADATA
simple_mysql-1.0.4.dist-info/WHEEL
simple_mysql-1.0.4.dist-info/top_level.txt
simple_mysql-1.0.4.dist-info/RECORD
